pandoc_latex_absolute_image/__init__.py
pandoc_latex_absolute_image/_main.py
pandoc_latex_absolute_image-0.2.0.1.dist-info/METADATA
pandoc_latex_absolute_image-0.2.0.1.dist-info/WHEEL
pandoc_latex_absolute_image-0.2.0.1.dist-info/entry_points.txt
pandoc_latex_absolute_image-0.2.0.1.dist-info/licenses/LICENSE
pandoc_latex_absolute_image-0.2.0.1.dist-info/RECORD
